tuspyserver/params.py
tuspyserver/request.py
tuspyserver/__init__.py
tuspyserver/file.py
tuspyserver/py.typed
tuspyserver/router.py
tuspyserver/info.py
tuspyserver/routes/creation.py
tuspyserver/routes/termination.py
tuspyserver/routes/__init__.py
tuspyserver/routes/core.py
tuspyserver-4.2.0.dist-info/WHEEL
tuspyserver-4.2.0.dist-info/METADATA
tuspyserver-4.2.0.dist-info/RECORD
