Metadata-Version: 2.3
Name: tuspyserver
Version: 4.2.0
Summary: A Python tus server implementation as a FastAPI router
Author: Edi Hasaj
Author-email: Edi Hasaj <edi.hasaj@applifyer.com>
Requires-Dist: fastapi>=0.110.0
Requires-Python: >=3.8
